{"title":"Combined feed","url":"https://LIFECORD.github.io/platform/all.xml","elements":[{"title":"[뉴페@스프] 결국 어떤 방식이 소비자에게 더 유리할까 (뉴스페퍼민트)","contents":"2023년 5월 26일","link":"https://newspeppermint.com/2023/05/25/npsp_creditcardbenefit/","retrieved":1685056375181},{"title":"[뉴페@스프] ‘얄팍한 나’로부터 벗어나려면 어떻게 하지? (뉴스페퍼민트)","contents":"2023년 5월 25일","link":"https://newspeppermint.com/2023/05/24/npsp_art/","retrieved":1684969996399},{"title":"쾌락에 고통이 뒤따른다는 건 과학적 진실 (뉴스페퍼민트)","contents":"2023년 5월 24일","link":"https://newspeppermint.com/2023/05/23/npsp_marijuanalegalization/","retrieved":1684901711610},{"title":"[뉴페@스프] 이것은 인터넷의 미래가 달린 질문이다 : 유튜브는 서점인가 언론사인가 (뉴스페퍼민트)","contents":"2023년 5월 24일","link":"https://newspeppermint.com/2023/05/23/npsp_gonzalezgoogle/","retrieved":1684883568652},{"title":"[뉴페@스프] 마스크 논란은 과학의 문제 그 이상이었다 (뉴스페퍼민트)","contents":"2023년 5월 22일","link":"https://newspeppermint.com/2023/05/21/npsp_maskmandates/","retrieved":1684717672651},{"title":"지금의 정치적 양극화에 미디어는 얼마나 책임이 있을까 (뉴스페퍼민트)","contents":"2023년 5월 22일","link":"https://newspeppermint.com/2023/05/21/npsp_conservativemedia/","retrieved":1684717672651},{"title":"[뉴페@스프] 우리가 미국의 전쟁 중독을 걱정해야 하는 이유 (뉴스페퍼민트)","contents":"2023년 5월 19일","link":"https://newspeppermint.com/2023/05/18/npsp_uswaraddiction/","retrieved":1684451548865},{"title":"“나한테 불리한데 왜 그래야 하지?”를 반박할 수 있을까 (뉴스페퍼민트)","contents":"2023년 5월 19일","link":"https://newspeppermint.com/2023/05/18/npsp_nothavingkids/","retrieved":1684419126240},{"title":"[뉴페@스프] 은혜를 모르는 호모 사피엔스로 남을 것인가 (뉴스페퍼민트)","contents":"2023년 5월 17일","link":"https://newspeppermint.com/2023/05/16/npsp_horseshoecrab/","retrieved":1684278773650},{"title":"[뉴페@스프] 그들의 ‘선한 의도’가 불러온 무시무시한 나비 효과 (뉴스페퍼민트)","contents":"2023년 5월 16일","link":"https://newspeppermint.com/2023/05/15/npsp_phonicsliteracy/","retrieved":1684192345608},{"title":"이 문제는 영영 풀지 못할 것이다, 이래도 되나? (뉴스페퍼민트)","contents":"2023년 5월 15일","link":"https://newspeppermint.com/2023/05/14/npsp_usgunviolence/","retrieved":1684112693367},{"title":"[뉴페@스프] 죽음에서 멀어지는 인간은 어떻게 살아야 할까 (뉴스페퍼민트)","contents":"2023년 5월 15일","link":"https://newspeppermint.com/2023/05/14/npsp_eternallife/","retrieved":1684105956332},{"title":"마지막 순간에도 그는 뼛속까지 음악가였습니다 (FIGK)","contents":"창작자로서 대중음악가가 유별난 점은 콘서트를 통해 청중을 일상적으로 마주한다는 점일 것입니다. 따라서 작업실이 주된 공간인 다른 장르의 작가들에게 수용자란 상상으로 만들어 낸 존재인 것과 달리 음악가들은 실재하는 구체적인 상황을 두고 작업물을 완성해갑니다. 심지어 자신의 장례식마저 그 상황이 될 수 있습니다. 류이치 사카모토가 자신의 장례식에서 틀 ‘마지막 플레이리스트’를 선곡한 것은 행위 자체로 뼛속까지 음악가였던 고인의 인생을 선명하게 드러냅니다. 플레이리스트에는 생전에 영향을 받았다고 밝혔던 바흐, 드뷔시, 라벨부터 엔니오 모리코네, 니노 로타 등의 33곡들이 포함되어 있습니다 그 마지막이 로렐 헤일로의 ‘Breathe (숨쉬다)’라는 데서 깨알 같은 유머 감각을 느끼며, 새삼 고인의 명복을 빕니다.&nbsp;<span style=\"color: rgb(255, 255, 255);\">&amp;&amp;</span><span class=\"styles_Conduct__F8R6P\">.......................................................................................................................................................</span>","link":"https://pitchfork.com/news/ryuichi-sakamotos-management-shares-his-last-playlist-which-he-prepared-for-his-own-funeral/","retrieved":1685096018255},{"title":"앤디 워홀은 저작권을 침해했는가 (FIGK)","contents":"전 세계 예술가들의 관심을 끌던 판결이 나왔다. ‘Orange Prince’(가수 프린스의 초상화)로 알려진 앤디 워홀의 작품이 있다. 프린스가 의뢰한 것도 아니고, 직접 그린 그림이 아닌 사진작가 골드스미스의 사진을 자르고 크기를 조정하며 색조를 바꾸는 변화를 거친 작품이다. 그의 대표작으로 꼽힐 만큼 큰 히트를 쳤었다. 2016년, 프린스의 사망 후 특집기사에 이 작품이 실린 것을 본 골드스미스가 자신의 사진이 도용되었다며 소송을 걸었으나 1차 재판에서 두 작품이 전달하는 메시지가 다르다며 워홀의 손을 들었다. 그리고, 지난주 열린 2차 판결에서는 워홀이 사진작가의 저작권을 침해했다는 판결이 나왔다. 저작권이라는 개념 자체가 옅어지는 시대, 이 상반된 두 입장을 읽고 난 후 당신의 의견이 궁금하다.&nbsp;<span style=\"color: rgb(255, 255, 255);\">&amp;</span><span class=\"styles_Conduct__F8R6P\">.....................................................................................................................................................................................................</span>","link":"https://edition.cnn.com/2023/05/18/politics/supreme-court-prince-andy-warhol/index.html","retrieved":1685096018256},{"title":"타인의 경험을 상상하는 능력 (FIGK)","contents":"사람은 자기 몫의 감각과 인지밖에 하지 못한다. 경험은 모두 제각각이다. 다수의 범주에 속한다면 살아가는 데에 큰 불편은 없지만, 조금만 다른 생활 경험을 가지게 되면 금세 큰 불편을 겪게 되는 것이 지금의 우리 사회다. 휠체어 이용자, 시력과 청력이 낮은 사람, 초고령자 등 신체, 감각, 인지 활동에 지원이 필요한 이들의 일상을 관찰하고 사례를 연구하며, 이를 제품과 공간, 디지털 서비스에 어떻게 적용할지 고민하는 매거진이 있다. 현재 이동, 직업, 놀이, 안전, 시니어라는 주제로 발간 중이며,  뉴스레터를 구독하면 다음 호의 글을 미리 받아볼 수 있다.  우리는 조금만 더 사려 깊게 타인의 경험을 상상할 필요가 있다. 그리고 그 상상력은 언젠가 우리 자신에게도 적용될 것이다. &nbsp;<span style=\"color: rgb(255, 255, 255);\"></span><span class=\"styles_Conduct__F8R6P\">.........................................................................................................................................................................</span>","link":"https://figk.net/www.magazinemsv.com","retrieved":1685096018256},{"title":"구토, 설사, 유머의 삼각형 (FIGK)","contents":"봉준호 감독이 스웨덴에서 태어나 &lt;설국열차&gt;와 &lt;기생충&gt;을 섞어 영화를 만들면 이런 느낌일까? feat. 약간의 SNS 트렌드를 곁들인. 루벤 외스틀룬드의 &lt;슬픔의 삼각형&gt;은 인스타그램으로 시작해 네이트판을 거쳐 마르크스, 레닌 서적으로 넘어갔다가 봉준호스러운 블랙 코미디로 ‘찝찝하게’ 마무리된다. 다만, 좀 더 더럽다. 미모로 계급 상승을 꿈꾸는 인플루언서, 환경과 평등의 가치를 모순적으로 주장하는 패션 업계에서 시작한 이 자본주의적 항해는 돈 많은 진상들이 타고 있는 호화 크루즈가 뒤집힘과 동시에 신박한 계급 사회로 쾌속 이동한다. 구토, 설사, 유머의 삼각형 덕분에 굽실거리느라 비위가 상할 대로 상한 우리의 위장 역시 뒤집힌다. 항마력 테스트하는 해리스 딕킨슨, 돌리 드 레옹 연기에 지사제 역시 필수.&nbsp;<span style=\"color: rgb(255, 255, 255);\">&amp;</span><span class=\"styles_Conduct__F8R6P\">...................................................................................................................................................</span>","link":"https://www.youtube.com/watch?v=hdz_HfJHIXY","retrieved":1685096018256},{"title":"뉴욕 웨스트 44번가 샌드위치 가게의 멋진 작별 인사 (FIGK)","contents":"한인 이민자 부부가 뉴욕에서 운영하던 ‘스타라이트 델리 샌드위치’가 39년 만에 문을 닫았다. 폐점 소식이 알려지자 단골들이 줄지어 방문하고 방송사에서 취재까지 나온다. 이들에게 스타라이트 델리는 어떤 곳이었을까. 하루 14시간씩 매일 누군가의 끼니를 성실히 책임지며 보낸 시간은 결국 멋진 송별회로 돌아왔다. 1만 7,839달러(한화 약 2,300만 원)의 퇴직금은 오랫동안 한자리에 있어준 것에 대한 단골들의 마음이었다. 브로드웨이 배우들이 과거에 공연을 마치고 가게에서 불렀던 노래를 다시 부른다. “너에게 행복한 길이길, 그때까지 늘 웃기를. 너에게 행복한 길이길, 우리가 다시 만날 때까지.” 가만히 노래를 듣는 부부의 얼굴엔 많은 것이 담긴다. 더욱 보기 어려워진 종류의 작별 인사다.&nbsp;<span style=\"color: rgb(255, 255, 255);\">&amp;&amp;&amp;</span><span class=\"styles_Conduct__F8R6P\">........................................................................................................................................................................................</span>","link":"https://www.youtube.com/watch?v=4DaRpF90C3o&feature=youtu.be","retrieved":1685096018256},{"title":"315개, 사라져간 코인 보고서 (FIGK)","contents":"315개. 2017년 4월부터 2023년 5월까지 국내 5대 거래소에서 거래 종료된 코인의 숫자다. 그중 김치 코인(국내 거래소에만 상장되어 있는 코인)의 비율은 총 96개로 30%였으며, 상장폐지까지 걸린 시간은 평균 2년이었다. 폐지 이유는 발행 후 사업을 진행하지 않은 프로젝트 위험이 48.9%로 높았고, 시세 조작이 의심되는 경우가 다음 순서였다. 상장 폐지된 코인의 25%는 홈페이지조차 연결이 되지 않았다. 이런 경우는 사실상 먹튀라고 할 수 있다. 강남 납치 살인 사건의 배경이 된 코인도 한 국회의원이 사랑하던 코인도 여기에 있다. 이처럼 한국일보 인터랙티브 기사에는 코인에 대한 부정적인 의견은 거둔 채 건조한 데이터로 채워져 있다. 대신 그 숫자가 말하는 팩트는 단순하고 선명하다.&nbsp;<span style=\"color: rgb(255, 255, 255);\">&amp;</span><span class=\"styles_Conduct__F8R6P\">............................................................................................................................</span>","link":"https://interactive.hankookilbo.com/v/delisted_coins/","retrieved":1685096018257},{"title":"환대의 영화제 (FIGK)","contents":"오늘날 많은 사람들은 난민, 추방, 실향, 이민 등 다양한 형태로 이주를 경험한다. 스스로 단일민족 국가라고 말해온 한국 역시 결혼이주여성, 이주노동자, 전쟁 난민, 라이따이한과 코피노 등 이미 오래전부터 다양하고 불균질한 구성원으로 가득한 공동체였다. 1902년 하와이로 떠나는 한국 최초의 이민선이 출발한 곳, 인천에서 제11회 디아스포라영화제가 한창이다. 개막식에 참석한 이후 나는 이 작고도 환대로 가득한 영화제와 사랑에 빠졌다. 다양한 피부색의 관객, 배리어 프리 상영관, 수어 통역, 어린아이를 위한 공간 등 곳곳에서 다양성을 포용하려는 시도가 느껴졌다. 한국에서 실로 오랜만에 느끼는 환대의 감각이었다.&nbsp;<span style=\"color: rgb(255, 255, 255);\"></span><span class=\"styles_Conduct__F8R6P\">......................................................................................................................................................................................</span>","link":"https://www.diaff.org/kor/addon/10000001/page.asp?page_num=34112","retrieved":1685096018259},{"title":"지구를 지키는 안젤리나 졸리의 방법 (FIGK)","contents":"패션업계가 가장 최근에 부딪힌 도덕적 딜레마는 섬유 쓰레기로 인한 오염 문제이다. 패스트 패션의 빠른 교체 주기와 저개발국가의 싼 노동력을 바탕으로 만들어내는 옷들이 전세계 토양과 해양의 플라스틱 오염과 탄소 문제의 주범으로 지적되고 있기 때문이다. 지난 17일 안젤리나 졸리는 이러한 패스트 패션의 문제들을 지적하며 업사이클링 패션 브랜드 아틀리에 졸리의 출범을 선언했다. 그녀의 새로운 패션기업은 재단사, 패턴 제작자, 장인들과  창의적인 소비자들이 협력하여 빈티지 섬유들과 재고 옷들에 새로운 생명을 불어넣는 디자인 플랫폼으로 성장하게 될 것이라고 한다. 이 회사에서는 난민 청소년들의 교육도 함께 이뤄질 것이라고 하니, 그녀의 회사가 패션과 지구의 미래에 어떤 변화를 가져올지 기대해도 좋을까? &nbsp;<span style=\"color: rgb(255, 255, 255);\"></span><span class=\"styles_Conduct__F8R6P\">..........................................................................................................................</span>","link":"https://www.atelierjolie.com/","retrieved":1685096018260},{"title":"우리의 안부를 재료 삼아 (FIGK)","contents":"매년 2,100여 명의 보호 대상 아동이 만 18세 이후 자립 생활을 시작한다. 아동복지시설과 위탁가정을 떠나 바로 홀로서기를 시작하기에 다소 이른 나이지만, 법은 그렇다. 배달과 인스턴트는 이들이 단순히 간편하다는 이유로 택한 식사가 아닐 수 있다. 식재료를 고르는 안목, 보관 방법, 합리적인 소비, 영양가 있는 식단 등 온전한 한 끼를 차리기 위해선 많은 시간과 경험을 투자해야 한다. KBS는 공영방송 50주년 기획으로 &lt;장바구니 집사들&gt;을 제작하였다. 충분한 준비가 되지 않은 상태에서 보호가 종료되는 청년들을 위해 집사 역할의 패널들이 함께 장바구니를 채운다. 차려주는 것이 아니라 함께 채워주는 것이야말로 삶에서 가장 중요한 ‘영위’를 알려주는 행위지 않을까. 때우지 말고 맛있게 먹어야 한다. 누구나.&nbsp;<span style=\"color: rgb(255, 255, 255);\">&amp;</span><span class=\"styles_Conduct__F8R6P\">......................................................................................................................................................................................................</span>","link":"https://www.youtube.com/watch?v=o7O1L59WdBM","retrieved":1685096018262}]}