{"title":"alookso ─ 둘러보기 ─ 최신 글","url":"https://alook.so/discover/latest","favicon":"https://alook.so/assets/favicon/favicon-32x32-8fc0ef8efcf005e31acc7291922e138cf3d3654531e4556566ca5cc4797a6793.png","elements":[{"title":"첫 승","contents":"<a class=\"text-lg text-gray-800 font-semibold line-clamp-2\" href=\"/posts/RGtPYw\">첫 승</a>","link":"https://alook.so/posts/RGtPYw","retrieved":1636514142533},{"title":"\"인도, 중국산 요소 80% 쓸어담아\" 요소 싹쓸이에 한국 요소수 대란.","contents":"<a class=\"text-lg text-gray-800 font-semibold line-clamp-2\" href=\"/posts/yEtKDj\">\"인도, 중국산 요소 80% 쓸어담아\" 요소 싹쓸이에 한국 요소수 대란.</a>","link":"https://alook.so/posts/yEtKDj","retrieved":1636514142534},{"title":"솔직히 나 하나 책임지기도 벅차...","contents":"<a class=\"text-lg text-gray-800 font-semibold line-clamp-2\" href=\"/posts/LKtMon\">솔직히 나 하나 책임지기도 벅차...</a>","link":"https://alook.so/posts/LKtMon","retrieved":1636514142537},{"title":"요즘 나는 무엇에 분노하는가.","contents":"<a class=\"text-lg text-gray-800 font-semibold line-clamp-2\" href=\"/posts/njtKDL\">요즘 나는 무엇에 분노하는가.</a>","link":"https://alook.so/posts/njtKDL","retrieved":1636514142538},{"title":"대기업 이직 후 새로운 직장에 대한 불안감..","contents":"<a class=\"text-lg text-gray-800 font-semibold line-clamp-2\" href=\"/posts/6MtjXL\">대기업 이직 후 새로운 직장에 대한 불안감..</a>","link":"https://alook.so/posts/6MtjXL","retrieved":1636514142539},{"title":"거절이 너무 힘들어요","contents":"<a class=\"text-lg text-gray-800 font-semibold line-clamp-2\" href=\"/posts/3wty8q\">거절이 너무 힘들어요</a>","link":"https://alook.so/posts/3wty8q","retrieved":1636514142541}]}