{"title":"alookso ─ 둘러보기 ─ 최신 글","url":"https://alook.so/discover/latest","favicon":"https://alook.so/assets/favicon/favicon-32x32-8fc0ef8efcf005e31acc7291922e138cf3d3654531e4556566ca5cc4797a6793.png","elements":[{"title":"친미 해야죠, 친중 할 순 없잖아요?","contents":"<a class=\"text-lg text-gray-800 font-semibold line-clamp-2\" href=\"/posts/WLtX9B\">친미 해야죠, 친중 할 순 없잖아요?</a>","link":"https://alook.so/posts/WLtX9B","retrieved":1635804803919},{"title":"꺼X, 너 존X 약하자나(벌크업한 이야기)-1","contents":"<a class=\"text-lg text-gray-800 font-semibold line-clamp-2\" href=\"/posts/0ktJq8\">꺼X, 너 존X 약하자나(벌크업한 이야기)-1</a>","link":"https://alook.so/posts/0ktJq8","retrieved":1635804803921},{"title":"엄마의 감정쓰레기통","contents":"<a class=\"text-lg text-gray-800 font-semibold line-clamp-2\" href=\"/posts/4Xtk24\">엄마의 감정쓰레기통</a>","link":"https://alook.so/posts/4Xtk24","retrieved":1635804803923},{"title":"개인보단 국가와 기업이 힘 써야될때","contents":"<a class=\"text-lg text-gray-800 font-semibold line-clamp-2\" href=\"/posts/w9txL8\">개인보단 국가와 기업이 힘 써야될때</a>","link":"https://alook.so/posts/w9txL8","retrieved":1635804803925}]}