{"title":"alookso ─ 둘러보기 ─ 최신 글","url":"https://alook.so/discover/latest","favicon":"https://alook.so/assets/favicon/favicon-32x32-8fc0ef8efcf005e31acc7291922e138cf3d3654531e4556566ca5cc4797a6793.png","elements":[{"title":"불행한가요?","contents":"<a class=\"text-lg text-gray-800 font-semibold line-clamp-2\" href=\"/posts/rDtb7W\">불행한가요?</a>","link":"https://alook.so/posts/rDtb7W","retrieved":1635956499679},{"title":"요즘 꽂힌건 영양제","contents":"<a class=\"text-lg text-gray-800 font-semibold line-clamp-2\" href=\"/posts/Zkt7Ww\">요즘 꽂힌건 영양제</a>","link":"https://alook.so/posts/Zkt7Ww","retrieved":1635956499680},{"title":"글쓰고 싶은데 돈도 벌고 싶다.","contents":"<a class=\"text-lg text-gray-800 font-semibold line-clamp-2\" href=\"/posts/dzt4DJ\">글쓰고 싶은데 돈도 벌고 싶다.</a>","link":"https://alook.so/posts/dzt4DJ","retrieved":1635956499680},{"title":"임차인 이면서 임대인이 느낀 점","contents":"<a class=\"text-lg text-gray-800 font-semibold line-clamp-2\" href=\"/posts/J5tbp1\">임차인 이면서 임대인이 느낀 점</a>","link":"https://alook.so/posts/J5tbp1","retrieved":1635956499681},{"title":"날 닮았다고? 이건 못참지","contents":"<a class=\"text-lg text-gray-800 font-semibold line-clamp-2\" href=\"/posts/potn3l\">날 닮았다고? 이건 못참지</a>","link":"https://alook.so/posts/potn3l","retrieved":1635956499682},{"title":"삼겹살을 안먹고 산다고요?","contents":"<a class=\"text-lg text-gray-800 font-semibold line-clamp-2\" href=\"/posts/eVtDYo\">삼겹살을 안먹고 산다고요?</a>","link":"https://alook.so/posts/eVtDYo","retrieved":1635956499683},{"title":"코로나 대처법","contents":"<a class=\"text-lg text-gray-800 font-semibold line-clamp-2\" href=\"/posts/PvtqW1\">코로나 대처법</a>","link":"https://alook.so/posts/PvtqW1","retrieved":1635956499685}]}