{"title":"alookso ─ 둘러보기 ─ 최신 글","url":"https://alook.so/discover/latest","favicon":"https://alook.so/assets/favicon/favicon-32x32-8fc0ef8efcf005e31acc7291922e138cf3d3654531e4556566ca5cc4797a6793.png","elements":[{"title":"신사임당은 페미니스트일까요?","contents":"<a class=\"text-lg text-gray-800 font-semibold line-clamp-2\" href=\"/posts/rDtzbV\">신사임당은 페미니스트일까요?</a>","link":"https://alook.so/posts/rDtzbV","retrieved":1638162848863},{"title":"숫자의 문제일까요?","contents":"<a class=\"text-lg text-gray-800 font-semibold line-clamp-2\" href=\"/posts/E7tVGL\">숫자의 문제일까요?</a>","link":"https://alook.so/posts/E7tVGL","retrieved":1638162848867},{"title":"코로나 검사를 하러 왔는데...","contents":"<a class=\"text-lg text-gray-800 font-semibold line-clamp-2\" href=\"/posts/Kmta7w\">코로나 검사를 하러 왔는데...</a>","link":"https://alook.so/posts/Kmta7w","retrieved":1638162848869},{"title":"선물 감사합니다.","contents":"<a class=\"text-lg text-gray-800 font-semibold line-clamp-2\" href=\"/posts/mbtpLn\">선물 감사합니다.</a>","link":"https://alook.so/posts/mbtpLn","retrieved":1638162848871},{"title":"카페에서 공부를 하는 일","contents":"<a class=\"text-lg text-gray-800 font-semibold line-clamp-2\" href=\"/posts/54tqpx\">카페에서 공부를 하는 일</a>","link":"https://alook.so/posts/54tqpx","retrieved":1638162848872},{"title":"이웃과 동맹","contents":"<a class=\"text-lg text-gray-800 font-semibold line-clamp-2\" href=\"/posts/q1ta0j\">이웃과 동맹</a>","link":"https://alook.so/posts/q1ta0j","retrieved":1638162848874}]}