{"title":"alookso ─ 둘러보기 ─ 최신 글","url":"https://alook.so/discover/latest","favicon":"https://alook.so/assets/favicon/favicon-32x32-8fc0ef8efcf005e31acc7291922e138cf3d3654531e4556566ca5cc4797a6793.png","elements":[{"title":"우울할때 어떻게 해야 할까?","contents":"<a class=\"text-lg text-gray-800 font-semibold line-clamp-2\" href=\"/posts/2xtEY5\">우울할때 어떻게 해야 할까?</a>","link":"https://alook.so/posts/2xtEY5","retrieved":1636978988380},{"title":"코로나시대에 중국에서 사는 가족","contents":"<a class=\"text-lg text-gray-800 font-semibold line-clamp-2\" href=\"/posts/WLtxok\">코로나시대에 중국에서 사는 가족</a>","link":"https://alook.so/posts/WLtxok","retrieved":1636978988382},{"title":"고민 상담","contents":"<a class=\"text-lg text-gray-800 font-semibold line-clamp-2\" href=\"/posts/0ktVzW\">고민 상담</a>","link":"https://alook.so/posts/0ktVzW","retrieved":1636978988384},{"title":"흥미로운 것이 없을 때","contents":"<a class=\"text-lg text-gray-800 font-semibold line-clamp-2\" href=\"/posts/M9tlzY\">흥미로운 것이 없을 때</a>","link":"https://alook.so/posts/M9tlzY","retrieved":1636978988386},{"title":"유엔의 새 기후변화협약, 글래스고 기후 조약을 아시나요?","contents":"<a class=\"text-lg text-gray-800 font-semibold line-clamp-2\" href=\"/posts/4Xt9na\">유엔의 새 기후변화협약, 글래스고 기후 조약을 아시나요?</a>","link":"https://alook.so/posts/4Xt9na","retrieved":1636978988388},{"title":"답글: 이팀장님이 이은진님??? 아~진짜? and 댓글 Continue~","contents":"<a class=\"text-lg text-gray-800 font-semibold line-clamp-2\" href=\"/posts/w9tRMk\">답글: 이팀장님이 이은진님??? 아~진짜? and 댓글 Continue~</a>","link":"https://alook.so/posts/w9tRMk","retrieved":1636978988390},{"title":"10년차 직장인 어디로 가야하죠?","contents":"<a class=\"text-lg text-gray-800 font-semibold line-clamp-2\" href=\"/posts/kZty2p\">10년차 직장인 어디로 가야하죠?</a>","link":"https://alook.so/posts/kZty2p","retrieved":1636974745491}]}