{"title":"alookso ─ 둘러보기 ─ 최신 글","url":"https://alook.so/discover/latest","favicon":"https://alook.so/assets/favicon/favicon-32x32-8fc0ef8efcf005e31acc7291922e138cf3d3654531e4556566ca5cc4797a6793.png","elements":[{"title":"부업에 꽂혔어요","contents":"<a class=\"text-lg text-gray-800 font-semibold line-clamp-2\" href=\"/posts/BatZ3r\">부업에 꽂혔어요</a>","link":"https://alook.so/posts/BatZ3r","retrieved":1639754140953},{"title":"조두순 둔기 폭행","contents":"<a class=\"text-lg text-gray-800 font-semibold line-clamp-2\" href=\"/posts/LKtv2r\">조두순 둔기 폭행</a>","link":"https://alook.so/posts/LKtv2r","retrieved":1639754140954},{"title":"안정성","contents":"<a class=\"text-lg text-gray-800 font-semibold line-clamp-2\" href=\"/posts/njt5Rd\">안정성</a>","link":"https://alook.so/posts/njt5Rd","retrieved":1639754140955},{"title":"군대가 시간이 가지 않는 이유, 시간을 빠르게 보내는 꿀팁!","contents":"<a class=\"text-lg text-gray-800 font-semibold line-clamp-2\" href=\"/posts/6Mt5LP\">군대가 시간이 가지 않는 이유, 시간을 빠르게 보내는 꿀팁!</a>","link":"https://alook.so/posts/6Mt5LP","retrieved":1639754140956},{"title":"핵심은,","contents":"<a class=\"text-lg text-gray-800 font-semibold line-clamp-2\" href=\"/posts/8Wtr9y\">핵심은,</a>","link":"https://alook.so/posts/8Wtr9y","retrieved":1639754140957},{"title":"상실감이 온다. 더 무서운 건 배고픔인가?","contents":"<a class=\"text-lg text-gray-800 font-semibold line-clamp-2\" href=\"/posts/G1tlme\">상실감이 온다. 더 무서운 건 배고픔인가?</a>","link":"https://alook.so/posts/G1tlme","retrieved":1639754140958},{"title":"좁쌀만 한 세상","contents":"<a class=\"text-lg text-gray-800 font-semibold line-clamp-2\" href=\"/posts/OEtXv7\">좁쌀만 한 세상</a>","link":"https://alook.so/posts/OEtXv7","retrieved":1639754140959},{"title":"퇴사 후 나의 삶","contents":"<a class=\"text-lg text-gray-800 font-semibold line-clamp-2\" href=\"/posts/E7tzo0\">퇴사 후 나의 삶</a>","link":"https://alook.so/posts/E7tzo0","retrieved":1639754140960}]}