{"title":"alookso ─ 둘러보기 ─ 최신 글","url":"https://alook.so/discover/latest","favicon":"https://alook.so/assets/favicon/favicon-32x32-8fc0ef8efcf005e31acc7291922e138cf3d3654531e4556566ca5cc4797a6793.png","elements":[{"title":"우유와 고기는 너무 맛있지만","contents":"<a class=\"text-lg text-gray-800 font-semibold line-clamp-2\" href=\"/posts/a0tM8K\">우유와 고기는 너무 맛있지만</a>","link":"https://alook.so/posts/a0tM8K","retrieved":1639190130435},{"title":"여러분들은 어떠한 주제로 대화를 나누시나요?","contents":"<a class=\"text-lg text-gray-800 font-semibold line-clamp-2\" href=\"/posts/J5tY5a\">여러분들은 어떠한 주제로 대화를 나누시나요?</a>","link":"https://alook.so/posts/J5tY5a","retrieved":1639190130436},{"title":"답글: 너무 감사했습니다.^^","contents":"<a class=\"text-lg text-gray-800 font-semibold line-clamp-2\" href=\"/posts/Pvt5OB\">답글: 너무 감사했습니다.^^</a>","link":"https://alook.so/posts/Pvt5OB","retrieved":1639190130437}]}