{"title":"alookso ─ 둘러보기 ─ 최신 글","url":"https://alook.so/discover/latest","favicon":"https://alook.so/assets/favicon/favicon-32x32-8fc0ef8efcf005e31acc7291922e138cf3d3654531e4556566ca5cc4797a6793.png","elements":[{"title":"애가 어른보다 낫다.","contents":"<a class=\"text-lg text-gray-800 font-semibold line-clamp-2\" href=\"/posts/YytPnB\">애가 어른보다 낫다.</a>","link":"https://alook.so/posts/YytPnB","retrieved":1637338864858},{"title":"그래도 축복이라고 생각해요","contents":"<a class=\"text-lg text-gray-800 font-semibold line-clamp-2\" href=\"/posts/E7tkDm\">그래도 축복이라고 생각해요</a>","link":"https://alook.so/posts/E7tkDm","retrieved":1637338864859},{"title":"폭력시위와 평화시위 이야기(2016)","contents":"<a class=\"text-lg text-gray-800 font-semibold line-clamp-2\" href=\"/posts/latG4G\">폭력시위와 평화시위 이야기(2016)</a>","link":"https://alook.so/posts/latG4G","retrieved":1637338864860},{"title":"좋은 부모가 되려는, 멋진 나 자신을 칭찬해!","contents":"<a class=\"text-lg text-gray-800 font-semibold line-clamp-2\" href=\"/posts/KmtxOP\">좋은 부모가 되려는, 멋진 나 자신을 칭찬해!</a>","link":"https://alook.so/posts/KmtxOP","retrieved":1637338864862},{"title":"제목이 먼저일까요? 내용이 먼저일까요?","contents":"<a class=\"text-lg text-gray-800 font-semibold line-clamp-2\" href=\"/posts/mbtYXL\">제목이 먼저일까요? 내용이 먼저일까요?</a>","link":"https://alook.so/posts/mbtYXL","retrieved":1637338864863}]}