{"title":"alookso ─ 둘러보기 ─ 최신 글","url":"https://alook.so/discover/latest","favicon":"https://alook.so/assets/favicon/favicon-32x32-8fc0ef8efcf005e31acc7291922e138cf3d3654531e4556566ca5cc4797a6793.png","elements":[{"title":"중요한 건 외모입니다.","contents":"<a class=\"text-lg text-gray-800 font-semibold line-clamp-2\" href=\"/posts/bWtLmw\">중요한 건 외모입니다.</a>","link":"https://alook.so/posts/bWtLmw","retrieved":1639142486997},{"title":"영어를 잘 하고 싶나요? 책 많이 읽고 한국어 공부하세요.","contents":"<a class=\"text-lg text-gray-800 font-semibold line-clamp-2\" href=\"/posts/a0tMx2\">영어를 잘 하고 싶나요? 책 많이 읽고 한국어 공부하세요.</a>","link":"https://alook.so/posts/a0tMx2","retrieved":1639142486999},{"title":"그 중심에는 민희진 크리에이티브 디렉터가 있다.","contents":"<a class=\"text-lg text-gray-800 font-semibold line-clamp-2\" href=\"/posts/Zkt07d\">그 중심에는 민희진 크리에이티브 디렉터가 있다.</a>","link":"https://alook.so/posts/Zkt07d","retrieved":1639142487001},{"title":"서울에 사는 지방인의 서러움","contents":"<a class=\"text-lg text-gray-800 font-semibold line-clamp-2\" href=\"/posts/J5tYb7\">서울에 사는 지방인의 서러움</a>","link":"https://alook.so/posts/J5tYb7","retrieved":1639142487002},{"title":"터키 리라화의 폭락","contents":"<a class=\"text-lg text-gray-800 font-semibold line-clamp-2\" href=\"/posts/pot9nv\">터키 리라화의 폭락</a>","link":"https://alook.so/posts/pot9nv","retrieved":1639142487002},{"title":"인구통계학, 가치, 줄어드는 인구","contents":"<a class=\"text-lg text-gray-800 font-semibold line-clamp-2\" href=\"/posts/Pvt5q6\">인구통계학, 가치, 줄어드는 인구</a>","link":"https://alook.so/posts/Pvt5q6","retrieved":1639142487003},{"title":"위드코로나","contents":"<a class=\"text-lg text-gray-800 font-semibold line-clamp-2\" href=\"/posts/zvtb1n\">위드코로나</a>","link":"https://alook.so/posts/zvtb1n","retrieved":1639142487005}]}