{"title":"alookso ─ 둘러보기 ─ 뜨는 글","url":"https://alook.so/discover","favicon":"https://alook.so/assets/favicon/favicon-32x32-8fc0ef8efcf005e31acc7291922e138cf3d3654531e4556566ca5cc4797a6793.png","elements":[{"title":"라면.... 좋아하시나요?","contents":"<a class=\"text-lg text-gray-800 font-semibold line-clamp-2\" href=\"/posts/q1t1Z9\">라면.... 좋아하시나요?</a>","link":"https://alook.so/posts/q1t1Z9","retrieved":1639901883303},{"title":"답글: 법도 타인의 것도 아닌 \"용서\", 그리고 \"복수\"","contents":"<a class=\"text-lg text-gray-800 font-semibold line-clamp-2\" href=\"/posts/rDtjdG\">답글: 법도 타인의 것도 아닌 \"용서\", 그리고 \"복수\"</a>","link":"https://alook.so/posts/rDtjdG","retrieved":1639898175557},{"title":"<이렇게 된 이상 청와대로 간다>와 팽길탄","contents":"<a class=\"text-lg text-gray-800 font-semibold line-clamp-2\" href=\"/posts/a0tMqO\">&lt;이렇게 된 이상 청와대로 간다&gt;와 팽길탄 </a>","link":"https://alook.so/posts/a0tMqO","retrieved":1639887565131},{"title":"[무비 무브 #11] 곡성 (2016, The Wailing); 영화보다 무서운 소리 없는 이 혼돈의 세상","contents":"<a class=\"text-lg text-gray-800 font-semibold line-clamp-2\" href=\"/posts/Zkt0jz\">[무비 무브 #11] 곡성 (2016, The Wailing); 영화보다 무서운 소리 없는 이 혼돈의 세상</a>","link":"https://alook.so/posts/Zkt0jz","retrieved":1639883734283},{"title":"부담스러웠을까","contents":"<a class=\"text-lg text-gray-800 font-semibold line-clamp-2\" href=\"/posts/eVtXWX\">부담스러웠을까</a>","link":"https://alook.so/posts/eVtXWX","retrieved":1639901883307},{"title":"휴가를 대하는 에디터팀의 자세","contents":"<a class=\"text-lg text-gray-800 font-semibold line-clamp-2\" href=\"/posts/Vntk8R\">휴가를 대하는 에디터팀의 자세</a>","link":"https://alook.so/posts/Vntk8R","retrieved":1639844492264},{"title":"법이 뭔데, 나 대신 용서한다는 거야?","contents":"<a class=\"text-lg text-gray-800 font-semibold line-clamp-2\" href=\"/posts/zvtbEp\">법이 뭔데, 나 대신 용서한다는 거야?</a>","link":"https://alook.so/posts/zvtbEp","retrieved":1639840551280},{"title":"휴가를 대하는 얼룩커들의 자세","contents":"<a class=\"text-lg text-gray-800 font-semibold line-clamp-2\" href=\"/posts/M9t2r7\">휴가를 대하는 얼룩커들의 자세</a>","link":"https://alook.so/posts/M9t2r7","retrieved":1639840551280},{"title":"[군생활 꿀팁] 군생활을 버티는 마법같은 10가지 주문","contents":"<a class=\"text-lg text-gray-800 font-semibold line-clamp-2\" href=\"/posts/kZtGWq\">[군생활 꿀팁] 군생활을 버티는 마법같은 10가지 주문</a>","link":"https://alook.so/posts/kZtGWq","retrieved":1639836876126},{"title":"답글: 경매학원 경험담이라니, 너무 재밌게 읽었어요!","contents":"<a class=\"text-lg text-gray-800 font-semibold line-clamp-2\" href=\"/posts/BatZdb\">답글: 경매학원 경험담이라니, 너무 재밌게 읽었어요!</a>","link":"https://alook.so/posts/BatZdb","retrieved":1639901883312},{"title":"답글: 부담없이 글 쓰는 습관 갖고 싶어서 활동 중입니다","contents":"<a class=\"text-lg text-gray-800 font-semibold line-clamp-2\" href=\"/posts/LKtvpD\">답글: 부담없이 글 쓰는 습관 갖고 싶어서 활동 중입니다</a>","link":"https://alook.so/posts/LKtvpD","retrieved":1639833675479},{"title":"답글: 충성! 얼룩소 자대에 새로 전입왔습니다.","contents":"<a class=\"text-lg text-gray-800 font-semibold line-clamp-2\" href=\"/posts/njt5LJ\">답글: 충성! 얼룩소 자대에 새로 전입왔습니다.</a>","link":"https://alook.so/posts/njt5LJ","retrieved":1639833675751},{"title":"답글: 끼리끼리 만나 결혼하는게 편하다.","contents":"<a class=\"text-lg text-gray-800 font-semibold line-clamp-2\" href=\"/posts/6Mt5zb\">답글: 끼리끼리 만나 결혼하는게 편하다.</a>","link":"https://alook.so/posts/6Mt5zb","retrieved":1639901883319}]}