{"title":"alookso ─ 둘러보기 ─ 최신 글","url":"https://alook.so/discover/latest","favicon":"https://alook.so/assets/favicon/favicon-32x32-8fc0ef8efcf005e31acc7291922e138cf3d3654531e4556566ca5cc4797a6793.png","elements":[{"title":"두 달 전 계획된 2년만의 만남..고민됩니다.","contents":"<a class=\"text-lg text-gray-800 font-semibold line-clamp-2\" href=\"/posts/rDtOZ2\">두 달 전 계획된 2년만의 만남..고민됩니다.</a>","link":"https://alook.so/posts/rDtOZ2","retrieved":1639030653639},{"title":"거인의 어깨에서 거인의 시야를 빌리자","contents":"<a class=\"text-lg text-gray-800 font-semibold line-clamp-2\" href=\"/posts/latPBa\">거인의 어깨에서 거인의 시야를 빌리자</a>","link":"https://alook.so/posts/latPBa","retrieved":1639030653639},{"title":"코로나19 확진자 7000명대 돌파...","contents":"<a class=\"text-lg text-gray-800 font-semibold line-clamp-2\" href=\"/posts/92t4MD\">코로나19 확진자 7000명대 돌파...</a>","link":"https://alook.so/posts/92t4MD","retrieved":1639030653640}]}