{"title":"alookso ─ 둘러보기 ─ 최신 글","url":"https://alook.so/discover/latest","favicon":"https://alook.so/assets/favicon/favicon-32x32-8fc0ef8efcf005e31acc7291922e138cf3d3654531e4556566ca5cc4797a6793.png","elements":[{"title":"불필요한 감정에 대해서","contents":"<a class=\"text-lg text-gray-800 font-semibold line-clamp-2\" href=\"/posts/70tz1b\">불필요한 감정에 대해서</a>","link":"https://alook.so/posts/70tz1b","retrieved":1637169515037},{"title":"‘실버 취준생 분투기’ 늦은 자유로의 여정.","contents":"<a class=\"text-lg text-gray-800 font-semibold line-clamp-2\" href=\"/posts/jdtGb0\">‘실버 취준생 분투기’ 늦은 자유로의 여정. </a>","link":"https://alook.so/posts/jdtGb0","retrieved":1637169515038},{"title":"답글: 첫 얼룩커픽? 나는 말이죠~","contents":"<a class=\"text-lg text-gray-800 font-semibold line-clamp-2\" href=\"/posts/bWtl1j\">답글: 첫 얼룩커픽? 나는 말이죠~</a>","link":"https://alook.so/posts/bWtl1j","retrieved":1637169515040},{"title":"국방비 어차피 늘어요","contents":"<a class=\"text-lg text-gray-800 font-semibold line-clamp-2\" href=\"/posts/potxJE\">국방비 어차피 늘어요 </a>","link":"https://alook.so/posts/potxJE","retrieved":1637169515041}]}