{"title":"alookso ─ 둘러보기 ─ 뜨는 글","url":"https://alook.so/discover/trendiest","favicon":"https://alook.so/assets/favicon/favicon-32x32-8fc0ef8efcf005e31acc7291922e138cf3d3654531e4556566ca5cc4797a6793.png","elements":[{"title":"카메라 뒤의 사람들","contents":"<a class=\"text-xl text-gray-800 font-semibold line-clamp-2\" href=\"/posts/Vntjnw\">카메라 뒤의 사람들</a>","link":"https://alook.so/posts/Vntjnw","retrieved":1634962670069},{"title":"나를 사로잡은 질문은 무엇입니까?: 20대 청년들의 이야기","contents":"<a class=\"text-xl text-gray-800 font-semibold line-clamp-2\" href=\"/posts/bWtpB3\">나를 사로잡은 질문은 무엇입니까?: 20대 청년들의 이야기</a>","link":"https://alook.so/posts/bWtpB3","retrieved":1634879641119},{"title":"그래서 저는 이 기사 제목이 참 맘에 들었답니다.","contents":"<a class=\"text-xl text-gray-800 font-semibold line-clamp-2\" href=\"/posts/mbtPED\">그래서 저는 이 기사 제목이 참 맘에 들었답니다.</a>","link":"https://alook.so/posts/mbtPED","retrieved":1634886898259},{"title":"내가 좋아하는 채식은?","contents":"<a class=\"text-xl text-gray-800 font-semibold line-clamp-2\" href=\"/posts/ZktmmX\">내가 좋아하는 채식은? </a>","link":"https://alook.so/posts/ZktmmX","retrieved":1634950162941},{"title":"중국은 유라시아에서 어느 정도의 존재감을 갖고 있을까","contents":"<a class=\"text-xl text-gray-800 font-semibold line-clamp-2\" href=\"/posts/WLtJkd\">중국은 유라시아에서 어느 정도의 존재감을 갖고 있을까</a>","link":"https://alook.so/posts/WLtJkd","retrieved":1634969786444},{"title":"오발","contents":"<a class=\"text-xl text-gray-800 font-semibold line-clamp-2\" href=\"/posts/njtoWB\">오발</a>","link":"https://alook.so/posts/njtoWB","retrieved":1634915673687},{"title":"100퍼센트가 아니면 실패인가요?","contents":"<a class=\"text-xl text-gray-800 font-semibold line-clamp-2\" href=\"/posts/J5tyzY\">100퍼센트가 아니면 실패인가요?</a>","link":"https://alook.so/posts/J5tyzY","retrieved":1634863974788},{"title":"광장이 없는 사회","contents":"<a class=\"text-xl text-gray-800 font-semibold line-clamp-2\" href=\"/posts/M9t04E\">광장이 없는 사회</a>","link":"https://alook.so/posts/M9t04E","retrieved":1634962670072},{"title":"기사 제목이 주는 감동과 여운","contents":"<a class=\"text-xl text-gray-800 font-semibold line-clamp-2\" href=\"/posts/njtoom\">기사 제목이 주는 감동과 여운</a>","link":"https://alook.so/posts/njtoom","retrieved":1634969786445},{"title":"왜 '그런 남자'를 계속 만나냐고요?","contents":"<a class=\"text-xl text-gray-800 font-semibold line-clamp-2\" href=\"/posts/XBt3Le\">왜 '그런 남자'를 계속 만나냐고요?</a>","link":"https://alook.so/posts/XBt3Le","retrieved":1634962670074},{"title":"당신이 생각한 최악의 상황은 정말 최악이 상황인가요?","contents":"<a class=\"text-xl text-gray-800 font-semibold line-clamp-2\" href=\"/posts/0ktm2J\">당신이 생각한 최악의 상황은 정말 최악이 상황인가요?</a>","link":"https://alook.so/posts/0ktm2J","retrieved":1634833980363},{"title":"\"사랑의매\"는 필요 할 까요? 필요 하지 않을까요?","contents":"<a class=\"text-xl text-gray-800 font-semibold line-clamp-2\" href=\"/posts/70tDm7\">\"사랑의매\"는 필요 할 까요? 필요 하지 않을까요?</a>","link":"https://alook.so/posts/70tDm7","retrieved":1634962670062},{"title":"일본은 '소득주도성장'을 꿈꾸는가","contents":"<a class=\"text-xl text-gray-800 font-semibold line-clamp-2\" href=\"/posts/Djtq6d\">일본은 '소득주도성장'을 꿈꾸는가</a>","link":"https://alook.so/posts/Djtq6d","retrieved":1634883428035},{"title":"법무부, '고 변희수 하사 강제 전역 부당' 육군에 항소 포기 지휘","contents":"<a class=\"text-xl text-gray-800 font-semibold line-clamp-2\" href=\"/posts/8Wt1kY\">법무부, '고 변희수 하사 강제 전역 부당' 육군에 항소 포기 지휘</a>","link":"https://alook.so/posts/8Wt1kY","retrieved":1634915673699},{"title":"미접종자가 접종을 주저하는 이유","contents":"<a class=\"text-xl text-gray-800 font-semibold line-clamp-2\" href=\"/posts/jdt5VX\"> 미접종자가 접종을 주저하는 이유</a>","link":"https://alook.so/posts/jdt5VX","retrieved":1634897849530}]}